kongfu_api/__init__.py
kongfu_api/db.py
kongfu_api/kongfu.py
kongfu_api/tool.py
kongfu_api-0.0.12.dist-info/METADATA
kongfu_api-0.0.12.dist-info/WHEEL
kongfu_api-0.0.12.dist-info/entry_points.txt
kongfu_api-0.0.12.dist-info/top_level.txt
kongfu_api-0.0.12.dist-info/RECORD
